invenio_oarepo_multilingual/__init__.py
invenio_oarepo_multilingual/version.py
invenio_oarepo_multilingual/included_mappings/v6/multilingual-v1.0.0.json
invenio_oarepo_multilingual/included_mappings/v7/multilingual-v1.0.0.json
invenio_oarepo_multilingual/jsonschemas/__init__.py
invenio_oarepo_multilingual/jsonschemas/multilingual-v1.0.0.json
invenio_oarepo_multilingual/marshmallow/__init__.py
invenio_oarepo_multilingual-1.1.2.dist-info/LICENSE
invenio_oarepo_multilingual-1.1.2.dist-info/METADATA
invenio_oarepo_multilingual-1.1.2.dist-info/WHEEL
invenio_oarepo_multilingual-1.1.2.dist-info/entry_points.txt
invenio_oarepo_multilingual-1.1.2.dist-info/top_level.txt
invenio_oarepo_multilingual-1.1.2.dist-info/RECORD
